Metadata-Version: 2.1
Name: LolzteamApi
Version: 1.1.22
Summary: A library that contains all the methods of the Lolzteam API (Market/Forum/Antipublic)
Home-page: https://github.com/AS7RIDENIED/Lolzteam_Python_Api
Author: AS7RID
Author-email: as7ridwork@gmail.com
Classifier: Programming Language :: Python :: 3.11
Requires-Python: >=3.9
License-File: LICENSE
